{"_path":"/code/problems","_dir":"code","_draft":false,"_partial":false,"_locale":"","_empty":false,"title":"疑难排查","description":"","body":{"type":"root","children":[{"type":"element","tag":"h1","props":{"id":"疑难排查"},"children":[{"type":"text","value":"疑难排查"}]},{"type":"element","tag":"ul","props":{},"children":[{"type":"element","tag":"li","props":{},"children":[{"type":"text","value":"Q: div标签设置背景时发现实际显示效果图片高度为0"},{"type":"element","tag":"br","props":{},"children":[]},{"type":"text","value":"\nA: 增加 padding-bottom 即可显示"}]},{"type":"element","tag":"li","props":{},"children":[{"type":"text","value":"Q: div background-image url路径错误 或者 该路径下无此文件"},{"type":"element","tag":"br","props":{},"children":[]},{"type":"text","value":"\nA: 增加多个url"}]},{"type":"element","tag":"li","props":{},"children":[{"type":"text","value":"Q: img src路径错误 或者 该路径下无此文件"},{"type":"element","tag":"br","props":{},"children":[]},{"type":"text","value":"\nA: onerror=\"this.src=''\""}]},{"type":"element","tag":"li","props":{},"children":[{"type":"text","value":"Q: 反思"},{"type":"element","tag":"br","props":{},"children":[]},{"type":"text","value":"\nA: 知识的匮乏让你想思考都没东西去思考"}]},{"type":"element","tag":"li","props":{},"children":[{"type":"text","value":"Q: css层级问题 div span 与 div > span"},{"type":"element","tag":"br","props":{},"children":[]},{"type":"text","value":"\nA: div span 设置是的div下的所有span div > span 设置的是紧挨着的二级span"}]},{"type":"element","tag":"li","props":{},"children":[{"type":"text","value":"Q: css文字竖向排列\nA: 标签writing-mode vertical-lr; 从左向右 从右向左是 vertical-rl;IE浏览器的从左向右 从右向左是tb-rl"}]},{"type":"element","tag":"li","props":{},"children":[{"type":"text","value":"Q: querySelector .开头和#开头"},{"type":"element","tag":"br","props":{},"children":[]},{"type":"text","value":"\nA: .开头是class #开头是id"}]},{"type":"element","tag":"li","props":{},"children":[{"type":"text","value":"Q: Linux删除某个字母开头的所有文件"},{"type":"element","tag":"br","props":{},"children":[]},{"type":"text","value":"\nA: 比如删除temp目录下以a开头的所有文件："},{"type":"element","tag":"br","props":{},"children":[]},{"type":"text","value":"首先要进到temp目录下"},{"type":"element","tag":"br","props":{},"children":[]},{"type":"text","value":"在删除前先使用ls a"},{"type":"element","tag":"em","props":{},"children":[{"type":"text","value":"查看要删除哪些文件，防止误删除"},{"type":"element","tag":"br","props":{},"children":[]},{"type":"text","value":"确认无误后，使用 rm -rf a"}]},{"type":"text","value":" 命令，删除a开头的所有文件"}]},{"type":"element","tag":"li","props":{},"children":[{"type":"text","value":"Q: slice不会改变原始数组"},{"type":"element","tag":"br","props":{},"children":[]},{"type":"text","value":"\nA:"}]},{"type":"element","tag":"li","props":{},"children":[{"type":"text","value":"Q: jQuery $ .# 区别"},{"type":"element","tag":"br","props":{},"children":[]},{"type":"text","value":"\nA: html自带标签 直接写标签 类用. id用#"}]},{"type":"element","tag":"li","props":{},"children":[{"type":"text","value":"Q: clion如何编译so库"},{"type":"element","tag":"br","props":{},"children":[]},{"type":"text","value":"\nA:"}]},{"type":"element","tag":"li","props":{},"children":[{"type":"text","value":"Q: clion如何链接使用dll库"},{"type":"element","tag":"br","props":{},"children":[]},{"type":"text","value":"\nA:"}]},{"type":"element","tag":"li","props":{},"children":[{"type":"text","value":"Q: run libuv, got \"Process finished with exit code -1073741515 (0xC0000135)\""},{"type":"element","tag":"br","props":{},"children":[]},{"type":"text","value":"\nA: if you are using visual studio toolchains in CLion, You need to paste in folder cmake-build-debug or\ncmake-build-release the files .dll, but no only SDL2_image.dll, all files from folder lib/x86.\nrefer "},{"type":"element","tag":"a","props":{"href":"https://stackoverflow.com/a/65268629/17744936","rel":["nofollow"]},"children":[{"type":"text","value":"https://stackoverflow.com/a/65268629/17744936"}]}]},{"type":"element","tag":"li","props":{},"children":[{"type":"text","value":"Q:"},{"type":"element","tag":"br","props":{},"children":[]},{"type":"text","value":"\nA:"}]}]}],"toc":{"title":"","searchDepth":2,"depth":2,"links":[]}},"_type":"markdown","_id":"content:3.code:problems.md","_source":"content","_file":"3.code/problems.md","_extension":"md"}