[{"_path":"/cpp/lib/bert","_dir":"lib","_draft":false,"_partial":false,"_locale":"","_empty":false,"title":"BERT","description":"","_type":"markdown","_id":"content:1.cpp:lib:bert.md","_source":"content","_file":"1.cpp/lib/bert.md","_extension":"md"},{"_path":"/cpp/lib/rapidjson","_dir":"lib","_draft":false,"_partial":false,"_locale":"","_empty":false,"title":"RapidJSON","description":"RapidJSON是一个C++的JSON解析器及生成器。","_type":"markdown","_id":"content:1.cpp:lib:RapidJSON.md","_source":"content","_file":"1.cpp/lib/RapidJSON.md","_extension":"md"}]